{
  "todo": [
    {
      "assignedTo": {
        "name": "lucas"
      },
      "creation_time": "2022-04-29T14:20:50.445Z",
      "id": "4",
      "references": [],
      "title": "Criar tabelas Mysql"
    },
    {
      "assignedTo": {
        "name": "lucas"
      },
      "creation_time": "2022-04-29T14:21:15.772Z",
      "id": "5",
      "references": [],
      "title": "Editar e excluir linhas de tabelas"
    },
    {
      "assignedTo": {
        "name": "lucas"
      },
      "creation_time": "2022-04-29T14:17:48.481Z",
      "id": "1",
      "references": [],
      "title": "fazer os campos com required (html)"
    },
    {
      "assignedTo": {
        "name": "lucas"
      },
      "creation_time": "2022-04-29T14:22:04.335Z",
      "id": "6",
      "references": [],
      "title": "Sistema de login salvo no BD"
    },
    {
      "assignedTo": {
        "name": "lucas"
      },
      "creation_time": "2022-04-29T14:18:10.817Z",
      "id": "2",
      "references": [],
      "title": "Validar se os campos foram preenchidos (JS)"
    },
    {
      "assignedTo": {
        "name": "lucas"
      },
      "creation_time": "2022-04-29T14:18:41.368Z",
      "id": "3",
      "references": [],
      "title": "Validar tudo (PHP)"
    }
  ],
  "in-progress": [],
  "testing": [],
  "done": []
}